vyper_lsp/__init__.py
vyper_lsp/__main__.py
vyper_lsp/ast.py
vyper_lsp/debounce.py
vyper_lsp/logging.py
vyper_lsp/main.py
vyper_lsp/navigation.py
vyper_lsp/utils.py
vyper_lsp/analyzer/__init__.py
vyper_lsp/grammar/__init__.py
vyper_lsp/grammar/grammar.lark
vyper_lsp/handlers/completion.py
vyper_lsp/handlers/hover.py
vyper_lsp/handlers/signatures.py
vyper_lsp-0.1.4.dist-info/METADATA
vyper_lsp-0.1.4.dist-info/WHEEL
vyper_lsp-0.1.4.dist-info/entry_points.txt
vyper_lsp-0.1.4.dist-info/licenses/LICENSE
vyper_lsp-0.1.4.dist-info/RECORD
