Metadata-Version: 2.4
Name: vyper-lsp
Version: 0.1.4
Summary: Language server for Vyper, a pythonic smart contract language
Author-email: z80 z80 <z80@ophy.xyz>
License-Expression: MIT
License-File: LICENSE
Keywords: lsp,vyper,vyper-lsp
Requires-Python: >=3.12
Requires-Dist: lark<2.0.0,>=1.1.7
Requires-Dist: lsprotocol<2024.0.0,>=2023.0.1
Requires-Dist: packaging<24.0.0,>=23.1.0
Requires-Dist: pygls<2.0.0,>=1.3.1
Requires-Dist: vyper<0.5.0,>=0.4.1
